macromax/__init__.py
macromax/bound.py
macromax/matrix.py
macromax/solver.py
macromax/backend/__init__.py
macromax/backend/numpy.py
macromax/backend/tensorflow.py
macromax/backend/torch.py
macromax/utils/__init__.py
macromax/utils/beam.py
macromax/utils/dim.py
macromax/utils/round125.py
macromax/utils/display/__init__.py
macromax/utils/display/colormap.py
macromax/utils/display/complex2rgb.py
macromax/utils/display/format_image_axes.py
macromax/utils/display/grid2extent.py
macromax/utils/display/hsv.py
macromax/utils/ft/__init__.py
macromax/utils/ft/ft_implementation.py
macromax/utils/ft/grid.py
macromax/utils/ft/subpixel.py
macromax-0.2.2.dist-info/METADATA
macromax-0.2.2.dist-info/WHEEL
macromax-0.2.2.dist-info/licenses/LICENSE.txt
macromax-0.2.2.dist-info/RECORD
