Metadata-Version: 2.3
Name: macromax
Version: 0.2.2
Summary: Library for solving macroscopic Maxwell's equations for electromagnetic waves in gain-free heterogeneous (bi-)(an)isotropic (non)magnetic materials. This is of particular interest to calculate the light field within complex, scattering, tissues.
Project-URL: Homepage, https://github.com/corilim/MacroMax/tree/master/python
Project-URL: Documentation, https://macromax.readthedocs.io/
Project-URL: Repository, https://github.com/corilim/MacroMax/
Project-URL: Issues, https://github.com/tttom/MacroMax/issues
Project-URL: Changelog, https://github.com/corilim/MacroMax/blob/master/python/CHANGES.md
Author-email: Tom Vettenburg <t.vettenburg@dundee.ac.uk>
License: MIT
Keywords: Maxwell,anisotropy,chiral,electromagnetic,heterogeneous,light,magnetic,optics,propagation,scattering
Classifier: Development Status :: 5 - Production/Stable
Classifier: License :: OSI Approved :: MIT License
Classifier: Programming Language :: Python :: 3
Classifier: Topic :: Scientific/Engineering :: Physics
Requires-Python: >=3.10
Requires-Dist: coloredlogs>=15.0.1
Requires-Dist: numpy>=1.26.4
Requires-Dist: scipy>=0.13.1
Provides-Extra: dev
Requires-Dist: build>=1.2.2; extra == 'dev'
Requires-Dist: memory-profiler>=0.61.0; extra == 'dev'
Requires-Dist: pprofile>=2.2.0; extra == 'dev'
Requires-Dist: setuptools>=66.1.1; extra == 'dev'
Requires-Dist: twine>=6.0.0; extra == 'dev'
Provides-Extra: doc
Requires-Dist: coloredlogs>=15.0.1; extra == 'doc'
Requires-Dist: docutils==0.20.1; extra == 'doc'
Requires-Dist: m2r2==0.3.3.post2; extra == 'doc'
Requires-Dist: matplotlib>=3.9.3; extra == 'doc'
Requires-Dist: numpy>=1.26.4; extra == 'doc'
Requires-Dist: recommonmark>=0.7.1; extra == 'doc'
Requires-Dist: scipy>=0.13.1; extra == 'doc'
Requires-Dist: sphinx-autodoc-typehints>=2.5.0; extra == 'doc'
Requires-Dist: sphinx-rtd-theme>=3.0.2; extra == 'doc'
Requires-Dist: sphinx>=8.1.3; extra == 'doc'
Requires-Dist: sphinxcontrib-mermaid>=1.0.0; extra == 'doc'
Provides-Extra: torch
Requires-Dist: torch>=2.5.1; extra == 'torch'
